{
    "version": "https://jsonfeed.org/version/1",
    "title": "Kim Gabe's DS Blog • All posts by \"판다스,데이터 병합,series,dataframe,to_dict,replace,merge,ref_df,인덱스,행정구역,엑셀 파일,csv 파일,인코딩,add_prefix\" tag",
    "description": "Kim Gabe의 블로그입니다. 데이터 사이언스, AI, 머신러닝 학습 과정을 기록합니다.",
    "home_page_url": "https://Kimgabe.github.io",
    "items": [
        {
            "id": "https://kimgabe.github.io/2025/07/18/04-%EB%8D%B0%EC%9D%B4%ED%84%B0-%ED%8C%8C%ED%8E%B8%ED%99%94-%EB%AC%B8%EC%A0%9C-%ED%8F%AC%EB%A7%B7%EC%9D%B4-%EB%8B%A4%EB%A5%B8-%EB%8D%B0%EC%9D%B4%ED%84%B0-%EB%B3%91%ED%95%A9-merge-2-%EC%B0%B8%EC%A1%B0-%EB%8D%B0%EC%9D%B4%ED%84%B0%EA%B0%80-%ED%95%84%EC%9A%94%ED%95%9C-%EA%B2%BD%EC%9A%B0-generated-version0/",
            "url": "https://kimgabe.github.io/2025/07/18/04-%EB%8D%B0%EC%9D%B4%ED%84%B0-%ED%8C%8C%ED%8E%B8%ED%99%94-%EB%AC%B8%EC%A0%9C-%ED%8F%AC%EB%A7%B7%EC%9D%B4-%EB%8B%A4%EB%A5%B8-%EB%8D%B0%EC%9D%B4%ED%84%B0-%EB%B3%91%ED%95%A9-merge-2-%EC%B0%B8%EC%A1%B0-%EB%8D%B0%EC%9D%B4%ED%84%B0%EA%B0%80-%ED%95%84%EC%9A%94%ED%95%9C-%EA%B2%BD%EC%9A%B0-generated-version0/",
            "title": "판다스를 활용한 데이터 병합 및 처리 기법 마스터하기",
            "date_published": "2025-07-17T15:00:00.000Z",
            "content_html": "<p>이 글에서는 판다스 라이브러리를 사용하여 데이터를 효율적으로 병합하고 처리하는 방법을 알아봅니다. 참조 데이터를 활용한 데이터 변환부터 병합까지의 전 과정을 단계별로 설명합니다. 데이터 분석에 필수적인 판다스 기능을 마스터하세요.</p>\n<p><strong>주요내용</strong></p>\n<ul>\n<li>📊 판다스 라이브러리의 기본 사용법 소개</li>\n<li>🔑 참조 데이터를 활용한 데이터 변환 방법</li>\n<li>🔄 데이터 병합 과정과 관련된 다양한 기법</li>\n</ul>\n<p>이 코드는  <code>os</code> 와  <code>pandas</code>  라이브러리를 임포트하고, Python에서 발생할 수 있는 불필요한 경고 메시지를 필터링하여 생략합니다. 또한, 현재 작업 중인 디렉토리의 경로를 얻어와서 이를 파일 로드 경로로 설정합니다. 이를 통해 사용자는 현재 작업 중인 디렉토리 내의 파일을 쉽게 접근하고 사용할 수 있습니다.</p>\n<figure class=\"highlight python\"><figcaption data-lang=\"python\"></figcaption><table><tr><td data-num=\"1\"></td><td><pre><span class=\"token keyword\">import</span> os</pre></td></tr><tr><td data-num=\"2\"></td><td><pre><span class=\"token keyword\">import</span> pandas <span class=\"token keyword\">as</span> pd</pre></td></tr><tr><td data-num=\"3\"></td><td><pre></pre></td></tr><tr><td data-num=\"4\"></td><td><pre><span class=\"token comment\"># 불필요한 경고 표시를 생략합니다.</span></pre></td></tr><tr><td data-num=\"5\"></td><td><pre><span class=\"token keyword\">import</span> warnings</pre></td></tr><tr><td data-num=\"6\"></td><td><pre>warnings<span class=\"token punctuation\">.</span>filterwarnings<span class=\"token punctuation\">(</span>action <span class=\"token operator\">=</span> <span class=\"token string\">'ignore'</span><span class=\"token punctuation\">)</span></pre></td></tr><tr><td data-num=\"7\"></td><td><pre></pre></td></tr><tr><td data-num=\"8\"></td><td><pre>a<span class=\"token operator\">=</span><span class=\"token operator\">%</span>pwd <span class=\"token comment\"># 현재 작업 경로를 변수 a에 할당합니다.</span></pre></td></tr><tr><td data-num=\"9\"></td><td><pre>os<span class=\"token punctuation\">.</span>chdir<span class=\"token punctuation\">(</span>a<span class=\"token punctuation\">)</span> <span class=\"token comment\"># 현재 작업 경로로 파일 로드 경로를 설정합니다.</span></pre></td></tr></table></figure><h1 id=\"참조-데이터가-필요한-경우\"><a class=\"anchor\" href=\"#참조-데이터가-필요한-경우\">#</a> 참조 데이터가 필요한 경우</h1>\n<hr />\n<ul>\n<li>\n<p>도로명 주소, 지번주소, 회원명, 회원 번호 등의 데이터는 보통  <code>일정한 패턴</code> 이 없고, 포맷도 다른 경우가 많다.</p>\n</li>\n<li>\n<p>이런 경우  <code>참조 데이터</code> 를 활용해서 변경한 뒤 merge를 하여 데이터 병합을 할 수 있다.</p>\n</li>\n</ul>\n<hr />\n<p><img src=\"https://user-images.githubusercontent.com/74717033/134629845-98277258-57e4-4ddd-8973-a66cbd492d34.png\" alt=\"image\" /></p>\n<hr />\n<p>e.g) 병합하고자 하는 데이터의 key값이 다른 경우</p>\n<ul>\n<li>a, b, c라고 되어있는 key값을 참조데이터를 활용해 각각 1, 2, 3으로 변경한 뒤에 merge를 진행한다.</li>\n</ul>\n<h1 id=\"관련-문법-1-seriesto_dict\"><a class=\"anchor\" href=\"#관련-문법-1-seriesto_dict\">#</a> 관련 문법 1 : Series.to_dict()</h1>\n<ul>\n<li>\n<p>Series의 index를 Key로, Data를 Value로 하는 dict형태로 변환해주는 함수</p>\n</li>\n<li>\n<p>replace 등 사전을 입력받는 함수를 사용할 때 주로 사용하는 함수입니다.</p>\n</li>\n<li>\n<p>index와 Data가 매칭되는 점을 유의해야 합니다.</p>\n<ul>\n<li>\n<p>일반적으로 참조 데이터를 불러올 때, data의 type가 Series가 아니라 DataFrame인 경우가 있습니다.</p>\n</li>\n<li>\n<p>이 경우 DataFrame에서 index와 Data를 설정해준 뒤에 dict로 바꿔줘야 합니다.</p>\n</li>\n</ul>\n</li>\n</ul>\n<h1 id=\"관련-문법-2-seriesreplace\"><a class=\"anchor\" href=\"#관련-문법-2-seriesreplace\">#</a> 관련 문법 2 : Series.replace()</h1>\n<hr />\n<ul>\n<li>\n<p>dict를 입력받아, Series 내에 있는 요소 가운데 key와 같은 값을 value로 변환해주는 함수</p>\n</li>\n<li>\n<p>'S' 라는 데이터의 value들을 변환해야 하는데, 아래 그림과 같은 dict를 replace()에 입력해주면, 이를 참조해서 값이 변경된다.</p>\n</li>\n</ul>\n<p><img src=\"https://user-images.githubusercontent.com/74717033/134629883-9638b21f-9745-41f2-8e6b-669a33da71df.png\" alt=\"image\" /></p>\n<hr />\n<ul>\n<li>만약, 'S' 데이터에 'e'라는 값이 있다면 (dict에는 'e'에 대한 참조 데이터가 없다), 이때의 결과값은 a~d는 dict가 반영된 위의 그림과 같이 결과가 나오고, e는 기존 S에 있던 값이 그대로 나오게 된다.</li>\n</ul>\n<hr />\n<h1 id=\"참조데이터를-통한-merge-실습\"><a class=\"anchor\" href=\"#참조데이터를-통한-merge-실습\">#</a> 참조데이터를 통한 merge 실습</h1>\n<p><strong>2011년 '군'이었던 것들이 '시'로 변경되어 데이터에 이를 적용하고자 할 때</strong></p>\n<p><img src=\"https://user-images.githubusercontent.com/74717033/134629895-41ca771b-b264-4e4b-9367-63c186b238f8.png\" alt=\"image\" /></p>\n<hr />\n<p><strong>팁.</strong> 데이터를 로드할 때, 원본 파일이 열려있으면 'Permission denied'라고 경고가 뜰 수 있습니다.</p>\n<hr />\n<p>이 문서는  <code>pandas</code>  라이브러리를 사용하여 CSV와 Excel 파일에서 데이터를 불러오는 방법을 설명합니다.  <code>pd.read_csv</code>  함수는 CSV 파일을 읽어서  <code>DataFrame</code>  객체로 반환합니다. 이 때,  <code>encoding</code>  파라미터를 사용하여 파일의 인코딩을 지정할 수 있습니다. Excel 파일에서는  <code>pd.read_excel</code>  함수를 사용하여 데이터를 불러옵니다.  <code>sheet_name</code>  파라미터를 통해 특정 시트의 데이터만 선택적으로 불러올 수 있으며, 여기서는 2020년과 2011년 데이터를 각각 불러오는 예시를 보여줍니다.</p>\n<figure class=\"highlight python\"><figcaption data-lang=\"python\"></figcaption><table><tr><td data-num=\"1\"></td><td><pre><span class=\"token comment\"># 데이터 불러오기</span></pre></td></tr><tr><td data-num=\"2\"></td><td><pre><span class=\"token comment\"># read_csv로 불러온 파일은 항상 'DataFrame' 이다.</span></pre></td></tr><tr><td data-num=\"3\"></td><td><pre></pre></td></tr><tr><td data-num=\"4\"></td><td><pre>ref_df <span class=\"token operator\">=</span> pd<span class=\"token punctuation\">.</span>read_csv<span class=\"token punctuation\">(</span><span class=\"token string\">\"시승격정보.csv\"</span><span class=\"token punctuation\">,</span> encoding <span class=\"token operator\">=</span> <span class=\"token string\">\"cp949\"</span><span class=\"token punctuation\">)</span>  <span class=\"token comment\"># 참고할 데이터</span></pre></td></tr><tr><td data-num=\"5\"></td><td><pre></pre></td></tr><tr><td data-num=\"6\"></td><td><pre><span class=\"token comment\"># sheet_name 파라미터를 활용해 특정 sheet의 값만 불러올 수도 있다.</span></pre></td></tr><tr><td data-num=\"7\"></td><td><pre>df1 <span class=\"token operator\">=</span> pd<span class=\"token punctuation\">.</span>read_excel<span class=\"token punctuation\">(</span><span class=\"token string\">\"인구수데이터.xlsx\"</span><span class=\"token punctuation\">,</span> sheet_name <span class=\"token operator\">=</span> <span class=\"token string\">\"202006\"</span><span class=\"token punctuation\">)</span> <span class=\"token comment\"># 2020년 데이터</span></pre></td></tr><tr><td data-num=\"8\"></td><td><pre>df2 <span class=\"token operator\">=</span> pd<span class=\"token punctuation\">.</span>read_excel<span class=\"token punctuation\">(</span><span class=\"token string\">\"인구수데이터.xlsx\"</span><span class=\"token punctuation\">,</span> sheet_name <span class=\"token operator\">=</span> <span class=\"token string\">\"201108\"</span><span class=\"token punctuation\">)</span> <span class=\"token comment\"># 2011년 데이터</span></pre></td></tr></table></figure><p>변수  <code>ref_df</code> 는 데이터 프레임을 참조합니다. 이 변수는 특정 데이터 분석이나 처리 과정에서 사용될 수 있으며, 데이터 프레임의 이름을 통해 데이터에 접근하거나 조작하는 데 사용됩니다.</p>\n<figure class=\"highlight python\"><figcaption data-lang=\"python\"></figcaption><table><tr><td data-num=\"1\"></td><td><pre>ref_df</pre></td></tr></table></figure><p>본 문서는 특정 코드 블록에 대한 설명을 제공하지 않습니다. 따라서, 구체적인 함수, 변수, 또는 클래스에 대한 설명을 제공할 수 없습니다.</p>\n<figure class=\"highlight python\"><figcaption data-lang=\"python\"></figcaption><table><tr><td data-num=\"1\"></td><td><pre><span class=\"token comment\"># df1에 대한 설명이나 주석을 추가할 코드가 없습니다.</span></pre></td></tr></table></figure><pre><code class=\"language-python\"></code></pre>\n<h2 id=\"series-형태로-type-변경\"><a class=\"anchor\" href=\"#series-형태로-type-변경\">#</a> Series 형태로 type 변경</h2>\n<hr />\n<ul>\n<li>\n<p>reference 데이터가 데이터 프레임 형태이기 때문에 to_dict()하기 위해 Series형태로 변경시켜줘야 합니다.</p>\n</li>\n<li>\n<p>Series의 index가 key가 되고, data가 value가 되도록 해야 합니다 -&gt; set_index를 활용해 '승격전' 컬럼을 인덱스로 설정</p>\n</li>\n</ul>\n<hr />\n<p>이 함수는  <code>ref_df</code>  데이터프레임에서  <code>'승격전'</code>  컬럼을 인덱스로 설정하고,  <code>'승격후'</code>  컬럼의 데이터를 선택하여 Series 객체를 반환합니다.  <code>set_index</code>  메서드를 사용하여 인덱스를 재설정하며, 이 과정을 통해 특정 컬럼의 값을 기반으로 새로운 Series 객체를 생성합니다.</p>\n<figure class=\"highlight python\"><figcaption data-lang=\"python\"></figcaption><table><tr><td data-num=\"1\"></td><td><pre><span class=\"token comment\"># index가 승격전이고, 데이터가 승격후인 Series</span></pre></td></tr><tr><td data-num=\"2\"></td><td><pre><span class=\"token comment\"># '승격전' 컬럼을 인덱스로 설정하기 위해 set_index를 활용</span></pre></td></tr><tr><td data-num=\"3\"></td><td><pre>ref_df<span class=\"token punctuation\">.</span>set_index<span class=\"token punctuation\">(</span><span class=\"token string\">'승격전'</span><span class=\"token punctuation\">)</span><span class=\"token punctuation\">[</span><span class=\"token string\">'승격후'</span><span class=\"token punctuation\">]</span></pre></td></tr></table></figure><p>인덱스 자료를 기반으로 대응되는 '승전후' 값을 dict 형태로 바꿔줍니다.</p>\n<p>이 함수는  <code>ref_df</code>  데이터프레임에서 '승격전' 열을 인덱스로 설정하고, '승격후' 열의 값을 이용하여 딕셔너리( <code>ref_dict</code> )를 생성합니다. 결과적으로, '승격전'의 값들이 키가 되고, '승격후'의 값들이 해당 키의 값이 되는 딕셔너리가 만들어집니다.</p>\n<figure class=\"highlight python\"><figcaption data-lang=\"python\"></figcaption><table><tr><td data-num=\"1\"></td><td><pre><span class=\"token comment\"># 인덱스 설정 및 시리즈를 딕셔너리로 변환</span></pre></td></tr><tr><td data-num=\"2\"></td><td><pre>ref_dict <span class=\"token operator\">=</span> ref_df<span class=\"token punctuation\">.</span>set_index<span class=\"token punctuation\">(</span><span class=\"token string\">'승격전'</span><span class=\"token punctuation\">)</span><span class=\"token punctuation\">[</span><span class=\"token string\">'승격후'</span><span class=\"token punctuation\">]</span><span class=\"token punctuation\">.</span>to_dict<span class=\"token punctuation\">(</span><span class=\"token punctuation\">)</span></pre></td></tr></table></figure><p>본 코드는  <code>df2</code>  데이터프레임에서 '행정구역' 열을 선택하는 작업을 수행합니다. 이때, '행정구역' 열에는 지역의 행정 구분이 '군'으로 표기되어 있음을 주석으로 명시합니다.</p>\n<figure class=\"highlight python\"><figcaption data-lang=\"python\"></figcaption><table><tr><td data-num=\"1\"></td><td><pre>df2<span class=\"token punctuation\">[</span><span class=\"token string\">'행정구역'</span><span class=\"token punctuation\">]</span> <span class=\"token comment\"># 행정구역이 '군'으로 표기되어 있다.</span></pre></td></tr></table></figure><p>ref_dict을 이용하여 키 변수 값 변환</p>\n<hr />\n<p>단계별로 생각해 봅시다.</p>\n<p>이 함수는  <code>df2</code> 의 '행정구역' 열에 있는 값을  <code>ref_dict</code> 를 사용하여 교체합니다. 교체 작업 후, '행정구역' 열의 값이 업데이트됩니다. 예를 들어, 특정 행정구역명이 '시'로 변경될 수 있습니다. 이 과정은 2011년의 행정구역명을 2020년의 행정구역명으로 매핑하는 데 사용됩니다.</p>\n<figure class=\"highlight python\"><figcaption data-lang=\"python\"></figcaption><table><tr><td data-num=\"1\"></td><td><pre><span class=\"token comment\"># 2011년의 행정구역명(df2)을 ref_dict를 참조하여 2020년의 행정구역명(df1)으로 교체합니다.</span></pre></td></tr><tr><td data-num=\"2\"></td><td><pre>df2<span class=\"token punctuation\">[</span><span class=\"token string\">'행정구역'</span><span class=\"token punctuation\">]</span> <span class=\"token operator\">=</span> df2<span class=\"token punctuation\">[</span><span class=\"token string\">'행정구역'</span><span class=\"token punctuation\">]</span><span class=\"token punctuation\">.</span>replace<span class=\"token punctuation\">(</span>ref_dict<span class=\"token punctuation\">)</span></pre></td></tr><tr><td data-num=\"3\"></td><td><pre>df2<span class=\"token punctuation\">[</span><span class=\"token string\">'행정구역'</span><span class=\"token punctuation\">]</span></pre></td></tr><tr><td data-num=\"4\"></td><td><pre><span class=\"token comment\"># 행정구역명이 '시'로 변경됩니다.</span></pre></td></tr></table></figure><h2 id=\"merge\"><a class=\"anchor\" href=\"#merge\">#</a> merge</h2>\n<hr />\n<ul>\n<li>df1과 df2에 있는  <code>변수명이 모두 같으므로</code> , 두 연도간의 데이터를 구분하기 위해 변수명 변경을 해줄 필요가 있다.</li>\n</ul>\n<hr />\n<p>데이터프레임  <code>df1</code> 과  <code>df2</code> 에서  <code>행정구역</code>  열을 인덱스로 설정합니다.  <code>inplace=True</code>  파라미터는 해당 변경사항을 원본 데이터프레임에 바로 적용함을 의미합니다.</p>\n<figure class=\"highlight python\"><figcaption data-lang=\"python\"></figcaption><table><tr><td data-num=\"1\"></td><td><pre>df1<span class=\"token punctuation\">.</span>set_index<span class=\"token punctuation\">(</span><span class=\"token string\">\"행정구역\"</span><span class=\"token punctuation\">,</span> inplace <span class=\"token operator\">=</span> <span class=\"token boolean\">True</span><span class=\"token punctuation\">)</span> <span class=\"token comment\"># 행정구역을 인덱스로 설정</span></pre></td></tr><tr><td data-num=\"2\"></td><td><pre>df2<span class=\"token punctuation\">.</span>set_index<span class=\"token punctuation\">(</span><span class=\"token string\">\"행정구역\"</span><span class=\"token punctuation\">,</span> inplace <span class=\"token operator\">=</span> <span class=\"token boolean\">True</span><span class=\"token punctuation\">)</span> <span class=\"token comment\"># 행정구역을 인덱스로 설정</span></pre></td></tr></table></figure><h3 id=\"add_prefix-함수로-데이터-구분하기\"><a class=\"anchor\" href=\"#add_prefix-함수로-데이터-구분하기\">#</a> add_prefix() 함수로 데이터 구분하기</h3>\n<ul>\n<li>\n<p>모든 컬럼에 접두사를 붙여주는 add_prefix() 함수를 활용해 2020년 데이터와 2011년 데이터를 구분해줍니다.</p>\n</li>\n<li>\n<p>add_prefix()를 쓰면 '모든 컬럼에 일괄적용' 되기 때문에 merge()에 활용할 '행정구역'은 index화 시켜 영향을 받지 않게 하였습니다.</p>\n</li>\n</ul>\n<p>데이터프레임의 컬럼명 앞에 특정 문자열을 추가하기 위해  <code>add_prefix</code>  메서드를 사용합니다. 이 예제에서는  <code>df1</code> 의 모든 컬럼명 앞에  <code>&quot;202006_&quot;</code> 을 추가하고,  <code>df2</code> 의 모든 컬럼명 앞에  <code>&quot;201108_&quot;</code> 을 추가합니다. 이 방법은 데이터를 로드할 때 각 데이터프레임의 출처나 날짜 등을 식별하기 위한 접두사(prefix)를 컬럼명에 쉽게 추가할 수 있게 해줍니다.</p>\n<figure class=\"highlight python\"><figcaption data-lang=\"python\"></figcaption><table><tr><td data-num=\"1\"></td><td><pre><span class=\"token comment\"># 데이터프레임의 컬럼명 앞에 특정 문자열을 추가</span></pre></td></tr><tr><td data-num=\"2\"></td><td><pre><span class=\"token comment\"># df1의 모든 컬럼명 앞에 '202006_'을 추가</span></pre></td></tr><tr><td data-num=\"3\"></td><td><pre><span class=\"token comment\"># df2의 모든 컬럼명 앞에 '201108_'을 추가</span></pre></td></tr><tr><td data-num=\"4\"></td><td><pre>df1 <span class=\"token operator\">=</span> df1<span class=\"token punctuation\">.</span>add_prefix<span class=\"token punctuation\">(</span><span class=\"token string\">\"202006_\"</span><span class=\"token punctuation\">)</span> </pre></td></tr><tr><td data-num=\"5\"></td><td><pre>df2 <span class=\"token operator\">=</span> df2<span class=\"token punctuation\">.</span>add_prefix<span class=\"token punctuation\">(</span><span class=\"token string\">\"201108_\"</span><span class=\"token punctuation\">)</span></pre></td></tr></table></figure><p>두 데이터 프레임  <code>df1</code> 과  <code>df2</code> 를 병합하는 과정에서, 각 데이터 프레임의 인덱스를 병합 기준으로 사용하기 위해  <code>pd.merge</code>  함수의  <code>left_index</code> 와  <code>right_index</code>  매개변수에  <code>True</code>  값을 설정합니다. 이 방식은 인덱스를 기준으로 두 데이터 프레임을 병합할 때 사용됩니다.</p>\n<figure class=\"highlight python\"><figcaption data-lang=\"python\"></figcaption><table><tr><td data-num=\"1\"></td><td><pre><span class=\"token comment\"># 각각의 데이터 프레임의 인덱스를 key 인덱스로 사용하기 위해 left_index = True, right_index = True를 적용</span></pre></td></tr><tr><td data-num=\"2\"></td><td><pre>merged_df <span class=\"token operator\">=</span> pd<span class=\"token punctuation\">.</span>merge<span class=\"token punctuation\">(</span>df1<span class=\"token punctuation\">,</span> df2<span class=\"token punctuation\">,</span> left_index <span class=\"token operator\">=</span> <span class=\"token boolean\">True</span><span class=\"token punctuation\">,</span> right_index <span class=\"token operator\">=</span> <span class=\"token boolean\">True</span><span class=\"token punctuation\">)</span></pre></td></tr></table></figure><p><code>merged_df.head()</code>  함수는 데이터프레임에서 처음 다섯 행을 반환합니다. 이는 데이터의 구조와 초기 몇 개의 값들을 빠르게 검토하기 위해 사용됩니다.</p>\n<figure class=\"highlight python\"><figcaption data-lang=\"python\"></figcaption><table><tr><td data-num=\"1\"></td><td><pre>merged_df<span class=\"token punctuation\">.</span>head<span class=\"token punctuation\">(</span><span class=\"token punctuation\">)</span> <span class=\"token comment\"># 데이터프레임의 처음 다섯 행을 출력합니다.</span></pre></td></tr></table></figure>",
            "tags": [
                "판다스,데이터 병합,Series,DataFrame,to_dict,replace,merge,ref_df,인덱스,행정구역,엑셀 파일,CSV 파일,인코딩,add_prefix"
            ]
        }
    ]
}